elastos_adenine/__init__.py
elastos_adenine/common.py
elastos_adenine/common_test.py
elastos_adenine/health_check.py
elastos_adenine/hive.py
elastos_adenine/hive_test.py
elastos_adenine/node_rpc.py
elastos_adenine/node_rpc_test.py
elastos_adenine/settings.py
elastos_adenine/sidechain_eth.py
elastos_adenine/sidechain_eth_test.py
elastos_adenine/wallet.py
elastos_adenine/wallet_test.py
elastos_adenine/stubs/__init__.py
elastos_adenine/stubs/common_pb2.py
elastos_adenine/stubs/common_pb2_grpc.py
elastos_adenine/stubs/health_check_pb2.py
elastos_adenine/stubs/health_check_pb2_grpc.py
elastos_adenine/stubs/hive_pb2.py
elastos_adenine/stubs/hive_pb2_grpc.py
elastos_adenine/stubs/node_rpc_pb2.py
elastos_adenine/stubs/node_rpc_pb2_grpc.py
elastos_adenine/stubs/sidechain_eth_pb2.py
elastos_adenine/stubs/sidechain_eth_pb2_grpc.py
elastos_adenine/stubs/wallet_pb2.py
elastos_adenine/stubs/wallet_pb2_grpc.py
test/__init__.py
test/py_test.py
elastos_adenine-2.0.3.dist-info/LICENSE
elastos_adenine-2.0.3.dist-info/METADATA
elastos_adenine-2.0.3.dist-info/WHEEL
elastos_adenine-2.0.3.dist-info/top_level.txt
elastos_adenine-2.0.3.dist-info/RECORD
