Metadata-Version: 2.1
Name: elastos-adenine
Version: 2.0.3
Summary: gRPC Client library to interact with Elastos Smartweb Service
Home-page: https://github.com/cyber-republic/python-grpc-adenine
Author: Kiran Pachhai
Author-email: kiran@tuum.tech
License: MIT
Keywords: elastos,smartweb-service,adenine
Platform: UNKNOWN
Classifier: Programming Language :: Python :: 3
Classifier: License :: OSI Approved :: MIT License
Classifier: Operating System :: OS Independent
Requires-Python: >=3.6
